licome/__init__.py
licome-2.0.0.dist-info/licenses/LICENSE
licome-2.0.0.dist-info/METADATA
licome-2.0.0.dist-info/WHEEL
licome-2.0.0.dist-info/top_level.txt
licome-2.0.0.dist-info/RECORD
